frxx/__init__.py
frxx/main.py
frxx-0.0.1.1.dist-info/licenses/LICENSE
frxx-0.0.1.1.dist-info/METADATA
frxx-0.0.1.1.dist-info/WHEEL
frxx-0.0.1.1.dist-info/top_level.txt
frxx-0.0.1.1.dist-info/RECORD
